vector_vis_graph/__init__.py
vector_vis_graph/vvg.py
vector_vis_graph/weight_calculation.py
vector_vis_graph-0.8.1.dist-info/licenses/LICENSE
vector_vis_graph-0.8.1.dist-info/METADATA
vector_vis_graph-0.8.1.dist-info/WHEEL
vector_vis_graph-0.8.1.dist-info/top_level.txt
vector_vis_graph-0.8.1.dist-info/RECORD
