Metadata-Version: 2.4
Name: vector-vis-graph
Version: 0.8.1
Summary: Vector visibility graph generation from multivariate time series.
Author-email: Tuna Alikaşifoğlu <tunakasif@gmail.com>
Classifier: Programming Language :: Python :: 3 :: Only
Classifier: Programming Language :: Python :: 3.10
Classifier: Programming Language :: Python :: 3.11
Classifier: Programming Language :: Python :: 3.12
Classifier: Programming Language :: Python :: 3.13
Requires-Python: <3.14,>=3.10
License-File: LICENSE
Requires-Dist: numba>=0.58.1
Requires-Dist: numpy>=1.26.2
Requires-Dist: scipy>=1.11.4
Dynamic: license-file
